{
  "Corn_Wasde_World": {
    "jsonUrl": "https://raw.githubusercontent.com/agfutures/json_all/main/wasde_Corn.json",
    "visuals": {
      "SND_History": {
        "filters": [
          { "key": "Attribute",  "field": "Attribute",  "type": "multiselect", "defaultAll": true },
          { "key": "MarketYear",  "field": "MarketYear",  "type": "multiselect", "defaultAll": true },
          { "key": "Region",      "field": "Region",      "type": "multiselect", "default": "United States" }
        ],
        "viz": ["WasdeChart"]
      },
      "Data_table": {
        "filters": [
          { "key": "Attribute",  "field": "Attribute",  "type": "multiselect", "defaultAll": true },
          { "key": "MarketYear",  "field": "MarketYear",  "type": "select",     "defaultMostRecent": true},
          { "key": "Region",      "field": "Region",      "type": "multiselect", "default": "United States" }
        ],
        "viz": ["WasdeTable"]
      },
      "Changes": {
        "filters": [
          { "key": "Attribute",  "field": "Attribute",  "type": "multiselect", "default": "Production" },
          { "key": "MarketYear",  "field": "MarketYear",  "type": "multiselect", "defaultCount": 5 },
          { "key": "Region",      "field": "Region",      "type": "select", "default": "United States" }

        ],
        "viz": ["WasdeChanges"]
      },
      "Global_snapshot": {
        "filters": [
          { "key": "Attribute",  "field": "Attribute",  "type": "multiselect", "defaultAll": true},
          { "key": "MarketYear",  "field": "MarketYear",  "type": "select", "defaultMostRecent": true },
          { "key": "Region",      "field": "Region",      "type": "multiselect", "defaultAll": true }

        ],
        "viz": ["WasdeGlobal"]
      }
    }
  },
  "Soybeans_Wasde_World": {
    "jsonUrl": "https://raw.githubusercontent.com/agfutures/json_all/main/wasde_Soybean.json",
    "visuals": {
      "WasdeChart": {
        "filters": [
          { "key": "Attribute",  "field": "Attribute",  "type": "multiselect", "defaultAll": true },
          { "key": "MarketYear",  "field": "MarketYear",  "type": "multiselect", "defaultAll": true },
          { "key": "Region",      "field": "Region",      "type": "multiselect", "default": "United States" }
        ],
        "viz": ["WasdeChart"]
      },
      "WasdeTable": {
        "filters": [
          { "key": "Attribute",  "field": "Attribute",  "type": "multiselect", "defaultAll": true },
          { "key": "MarketYear",  "field": "MarketYear",  "type": "select",      "defaultMostRecent": true  },
          { "key": "Region",      "field": "Region",      "type": "multiselect", "default": "United States" }
        ],
        "viz": ["WasdeTable"]
      },
      "WasdeChanges": {
        "filters": [
          { "key": "Attribute",  "field": "Attribute",  "type": "multiselect", "default": "Production" },
          { "key": "MarketYear",  "field": "MarketYear",  "type": "multiselect", "defaultCount": 5 },
          { "key": "Region",      "field": "Region",      "type": "select", "default": "United States" }

        ],
        "viz": ["WasdeChanges"]
      },
      "WasdeGlobal": {
        "filters": [
          { "key": "Attribute",  "field": "Attribute",  "type": "multiselect", "defaultAll": true},
          { "key": "MarketYear",  "field": "MarketYear",  "type": "select", "defaultMostRecent": true },
          { "key": "Region",      "field": "Region",      "type": "multiselect", "defaultAll": true }

        ],
        "viz": ["WasdeGlobal"]
      }    
    }
  }
}
